mumichaspy/__init__.py
mumichaspy/fastapi_jwt_chassis/__init__.py
mumichaspy/fastapi_jwt_chassis/config.py
mumichaspy/fastapi_jwt_chassis/mocks.py
mumichaspy/fastapi_jwt_chassis/time.py
mumichaspy/fastapi_jwt_chassis/validation.py
mumichaspy/sqlalchemy_chassis/__init__.py
mumichaspy/sqlalchemy_chassis/config.py
mumichaspy/sqlalchemy_chassis/crud.py
mumichaspy/sqlalchemy_chassis/database.py
mumichaspy/sqlalchemy_chassis/mocks.py
mumichaspy/sqlalchemy_chassis/testing_helpers.py
mumichaspy-1.0.8.dist-info/LICENSE
mumichaspy-1.0.8.dist-info/METADATA
mumichaspy-1.0.8.dist-info/WHEEL
mumichaspy-1.0.8.dist-info/top_level.txt
mumichaspy-1.0.8.dist-info/RECORD
