Metadata-Version: 2.1
Name: mumichaspy
Version: 1.0.8
Summary: An implementation of Microservice Chassis pattern in Python
Author-email: Alain PEREZ RIAÑO <aperez@mondragon.edu>
Project-URL: Homepage, https://github.com/mu-sse/mumichaspy
Project-URL: Issues, https://github.com/mu-sse/mumichaspy/issues
Classifier: Programming Language :: Python :: 3
Classifier: License :: OSI Approved :: MIT License
Classifier: Operating System :: OS Independent
Requires-Python: >=3.8
License-File: LICENSE
Requires-Dist: sqlalchemy ~=2.0
Requires-Dist: fastapi ~=0.109
Requires-Dist: pyjwt[crypto] ~=2.8
Requires-Dist: httpx ~=0.26
Requires-Dist: pytz ~=2024.1
Provides-Extra: test
Requires-Dist: pytest ~=7.0 ; extra == 'test'
Requires-Dist: aiosqlite ~=0.19 ; extra == 'test'
Requires-Dist: pytest-asyncio ~=0.15 ; extra == 'test'
